.gitignore
LICENSE
MANIFEST.in
README.rst
setup.py
btrfs_sxbackup/__init__.py
btrfs_sxbackup/__main__.py
btrfs_sxbackup/core.py
btrfs_sxbackup/entities.py
btrfs_sxbackup/mail.py
btrfs_sxbackup/retention.py
btrfs_sxbackup/shell.py
btrfs_sxbackup.egg-info/PKG-INFO
btrfs_sxbackup.egg-info/SOURCES.txt
btrfs_sxbackup.egg-info/dependency_links.txt
btrfs_sxbackup.egg-info/entry_points.txt
btrfs_sxbackup.egg-info/top_level.txt
btrfs_sxbackup/tests/TestKeepExpression.py
btrfs_sxbackup/tests/TestSnapshotName.py
btrfs_sxbackup/tests/__init__.py
etc/btrfs-sxbackup.conf