Metadata-Version: 1.1
Name: btrfs-sxbackup
Version: 0.6.6
Summary: Incremental btrfs snapshot backups with push/pull support via SSH
Home-page: https://github.com/masc3d/btrfs-sxbackup
Author: Marco Schindler
Author-email: masc@disappear.de
License: GNU GPL
Platform: UNKNOWN
Classifier: Environment :: Console
Classifier: Intended Audience :: End Users/Desktop
Classifier: Intended Audience :: System Administrators
Classifier: License :: OSI Approved :: GNU General Public License (GPL)
Classifier: Operating System :: POSIX :: Linux
Classifier: Programming Language :: Python :: 3 :: Only
Classifier: Topic :: System :: Filesystems
Classifier: Topic :: System :: Archiving :: Backup
Classifier: Topic :: Utilities
